pywrapid/__init__.py
pywrapid/config/__init__.py
pywrapid/config/config.py
pywrapid/config/exceptions.py
pywrapid/config/requirements.txt
pywrapid/log/__init__.py
pywrapid/log/application_log.py
pywrapid/utils/__init__.py
pywrapid/utils/dict_tools.py
pywrapid/utils/exceptions.py
pywrapid/utils/filesystem_tools.py
pywrapid/webclient/__init__.py
pywrapid/webclient/exceptions.py
pywrapid/webclient/requirements.txt
pywrapid/webclient/web.py
pywrapid-0.3.6.dist-info/licenses/LICENSE
pywrapid-0.3.6.dist-info/METADATA
pywrapid-0.3.6.dist-info/WHEEL
pywrapid-0.3.6.dist-info/top_level.txt
pywrapid-0.3.6.dist-info/RECORD
