Metadata-Version: 2.4
Name: pywrapid
Version: 0.3.6
Summary: Collection of wrapper libraries for rapid development of python applications
Author-email: Jonas Werme <jonas.werme@nsahq.se>, Marcus Wallgren <marcus.wallgren@nsahq.se>
Maintainer-email: Jonas Werme <jonas.werme@nsahq.se>, Marcus Wallgren <marcus.wallgren@nsahq.se>
License: MIT License
Project-URL: homepage, https://github.com/nsahq
Project-URL: documentation, https://pywrapid.readthedocs.io/en/latest/
Project-URL: repository, https://github.com/nsahq/pywrapid
Project-URL: changelog, https://github.com/nsahq/pywrapid
Keywords: web client,requests,config,yaml config,wrapper
Classifier: Programming Language :: Python
Classifier: Programming Language :: Python :: 3
Classifier: Programming Language :: Python :: 3.7
Classifier: Programming Language :: Python :: 3.8
Classifier: Programming Language :: Python :: 3.9
Classifier: Programming Language :: Python :: 3.10
Classifier: Programming Language :: Python :: 3.11
Classifier: Programming Language :: Python :: 3.12
Classifier: Programming Language :: Python :: Implementation
Classifier: Programming Language :: Python :: Implementation :: CPython
Classifier: Programming Language :: Python :: Implementation :: PyPy
Classifier: Development Status :: 3 - Alpha
Classifier: Operating System :: OS Independent
Requires-Python: >=3.7
License-File: LICENSE
Provides-Extra: yaml
Requires-Dist: pyyaml>=5.1; extra == "yaml"
Provides-Extra: requests
Requires-Dist: requests>=2.25.0; extra == "requests"
Provides-Extra: httpx
Requires-Dist: httpx>=0.18.0; extra == "httpx"
Provides-Extra: aiohttp
Requires-Dist: aiohttp>=3.7.0; extra == "aiohttp"
Provides-Extra: jwt
Requires-Dist: pyjwt; extra == "jwt"
Provides-Extra: webclient
Requires-Dist: pywrapid[requests]; extra == "webclient"
Provides-Extra: webclient-async
Requires-Dist: pywrapid[webclient-aiohttp]; extra == "webclient-async"
Provides-Extra: standard
Requires-Dist: pywrapid[jwt,webclient,yaml]; extra == "standard"
Provides-Extra: all
Requires-Dist: pywrapid[jwt,webclient,yaml]; extra == "all"
Provides-Extra: qa
Requires-Dist: pywrapid[lint,security,tests]; extra == "qa"
Provides-Extra: dev
Requires-Dist: pywrapid[all,build,docs,qa,tests]; extra == "dev"
Provides-Extra: tests
Requires-Dist: pytest>=7.0.0; extra == "tests"
Requires-Dist: pytest-cov>=4.0.0; extra == "tests"
Requires-Dist: tox>=4.2.0; extra == "tests"
Requires-Dist: responses>=0.21.0; extra == "tests"
Requires-Dist: pytest-asyncio>=0.21.0; extra == "tests"
Requires-Dist: coverage>=7.0.0; extra == "tests"
Provides-Extra: lint
Requires-Dist: black>=23.0.0; extra == "lint"
Requires-Dist: isort>=5.12.0; extra == "lint"
Requires-Dist: flake8>=6.0.0; extra == "lint"
Requires-Dist: flake8-pyproject; extra == "lint"
Requires-Dist: mypy>=1.0.0; extra == "lint"
Requires-Dist: pylint>=2.17.0; extra == "lint"
Requires-Dist: types-PyYAML; extra == "lint"
Requires-Dist: types-requests; extra == "lint"
Provides-Extra: security
Requires-Dist: bandit; extra == "security"
Requires-Dist: safety; extra == "security"
Provides-Extra: docs
Requires-Dist: sphinx>=7.0.0; extra == "docs"
Requires-Dist: sphinx_autodoc_typehints>=1.24.0; extra == "docs"
Requires-Dist: sphinx_rtd_theme>=1.3.0; extra == "docs"
Requires-Dist: pyyaml>=5.1; extra == "docs"
Requires-Dist: pyjwt; extra == "docs"
Provides-Extra: build
Requires-Dist: build>=1.0.0; extra == "build"
Requires-Dist: twine>=4.0.0; extra == "build"
Dynamic: license-file
